README.md
setup.py
phonebook_api/__init__.py
phonebook_api/api_client.py
phonebook_api/configuration.py
phonebook_api/rest.py
phonebook_api.egg-info/PKG-INFO
phonebook_api.egg-info/SOURCES.txt
phonebook_api.egg-info/dependency_links.txt
phonebook_api.egg-info/requires.txt
phonebook_api.egg-info/top_level.txt
phonebook_api/api/__init__.py
phonebook_api/api/blacklist_api.py
phonebook_api/models/__init__.py
phonebook_api/models/error_item.py
phonebook_api/models/error_response.py
phonebook_api/models/fetch_blacklist_success.py
phonebook_api/models/number_to_blacklist.py
phonebook_api/models/response_error_code.py
phonebook_api/models/response_error_title.py
test/__init__.py
test/test_blacklist_api.py
test/test_error_item.py
test/test_error_response.py
test/test_fetch_blacklist_success.py
test/test_number_to_blacklist.py
test/test_response_error_code.py
test/test_response_error_title.py