Metadata-Version: 1.0
Name: phonebook-api
Version: 0.0.1
Summary: Phonebook API
Home-page: https://messente.com/documentation
Author: UNKNOWN
Author-email: messente@messente.com
License: UNKNOWN
Keywords: OpenAPI,OpenAPI-Generator,Phonebook API
Platform: UNKNOWN
